pdfp/button_widget.py
pdfp/file_tree_widget.py
pdfp/images/logo.ico
pdfp/log_widget.py
pdfp/main.py
pdfp/main_window.py
pdfp/operations/clean_copy.py
pdfp/operations/crop.py
pdfp/operations/file2pdf.py
pdfp/operations/ocr.py
pdfp/operations/png.py
pdfp/operations/trim.py
pdfp/operations/tts.py
pdfp/progress_widget.py
pdfp/settings_window.py
pdfp/utils/clean_text.py
pdfp/utils/filename_constructor.py
pdfp/utils/tts_limit.py
pdfp-0.2.1.dist-info/LICENSE
pdfp-0.2.1.dist-info/METADATA
pdfp-0.2.1.dist-info/WHEEL
pdfp-0.2.1.dist-info/entry_points.txt
pdfp-0.2.1.dist-info/RECORD
