Metadata-Version: 2.1
Name: pdfp
Version: 0.2.1
Summary: PDF Processor - a GUI for some common PDF operations.
Home-page: https://github.com/MellowKyler/pdfp
License: AGPL-3.0-only
Author: Dreary
Author-email: drearywillowdev@gmail.com
Requires-Python: >=3.10,<3.13
Classifier: License :: OSI Approved :: GNU Affero General Public License v3
Classifier: Programming Language :: Python :: 3
Classifier: Programming Language :: Python :: 3.10
Classifier: Programming Language :: Python :: 3.11
Classifier: Programming Language :: Python :: 3.12
Requires-Dist: PySide6 (>=6.5.0,<7.0.0)
Requires-Dist: gtts (>=2.5.1,<3.0.0)
Requires-Dist: ocrmypdf (>=16.4.1,<17.0.0)
Requires-Dist: pymupdf (>=1.24.7,<2.0.0)
Requires-Dist: send2trash (>=1.8.3,<2.0.0)
Project-URL: Issues, https://github.com/MellowKyler/pdfp/issues
Project-URL: PyPi, https://pypi.org/project/pdfp/
Project-URL: Source, https://github.com/MellowKyler/pdfp
